<?xml version="1.0" encoding="UTF-8" ?>
<connectdelay value="5000"/>
<servers/>
<associations>
	<name value="c2c12"/>
	<association name="c2c12" assoctype="CLIENT" hostAddress="217.167.15.187" hostPort="2800" peerAddress="193.249.223.248" peerPort="2839" serverName="" ipChannelType="0" extraHostAddresseSize="1">
		<extraHostAddress value="217.167.15.171"/>
  </association>

	<name value="c2c22"/>
	<association name="c2c22" assoctype="CLIENT" hostAddress="217.167.15.171" hostPort="2803" peerAddress="193.249.223.136" peerPort="2839" serverName="" ipChannelType="0" extraHostAddresseSize="1">
		<extraHostAddress value="217.167.15.187"/>
  </association>

</associations>
